{"cameraMode":{"drawMode":0,"name":"Shaded","section":"Shading Mode"},"sceneLighting":true,"audioPlay":false,"sceneViewState":{"showFog":true,"showMaterialUpdate":false,"showSkybox":true,"showFlares":true,"showImageEffects":true,"showParticleSystems":true},"in2DMode":false,"pivot":{"x":-4.760631084442139,"y":14.893253326416016,"z":-11.270469665527344},"rotation":{"x":-0.5735304355621338,"y":-0.004681233316659927,"z":0.0032826357055455448,"w":-0.8191823363304138},"size":56.091304779052737,"orthographic":false}